bttv/__init__.py
bttv/cv_utils.py
bttv/gen_simulation_data.py
bttv/grad_utils.py
bttv/opt_utils.py
bttv-0.1.0.dist-info/AUTHORS.rst
bttv-0.1.0.dist-info/LICENSE
bttv-0.1.0.dist-info/METADATA
bttv-0.1.0.dist-info/WHEEL
bttv-0.1.0.dist-info/top_level.txt
bttv-0.1.0.dist-info/RECORD
