Metadata-Version: 2.1
Name: bttv
Version: 0.1.0
Summary: Tools for a implementing time-varying Bradley-Terry rankings
Home-page: https://github.com/shamindras/bttv
Author: Heejong Bong <blueconet@gmail.com>, Wanshan Li <wanshanl@andrew.cmu.edu>, Shamindra Shrotriya <shamindra.shrotriya@gmail.com>
Author-email: shamindra.shrotriya@gmail.com
License: MIT
Keywords: bttv
Platform: UNKNOWN
Classifier: Programming Language :: Python :: 3
Classifier: Programming Language :: Python :: Implementation :: PyPy
Classifier: License :: OSI Approved :: MIT License
Classifier: Natural Language :: English
Requires-Python: >=3.6
